francium_result_test/__init__.py
francium_result_test/py.typed
francium_result_test/result.py
francium_result_test-0.7.0.dist-info/LICENSE
francium_result_test-0.7.0.dist-info/METADATA
francium_result_test-0.7.0.dist-info/WHEEL
francium_result_test-0.7.0.dist-info/top_level.txt
francium_result_test-0.7.0.dist-info/zip-safe
francium_result_test-0.7.0.dist-info/RECORD
