Metadata-Version: 2.1
Name: francium-result-test
Version: 0.7.0
Summary: A Rust-like result type for Python
Home-page: https://github.com/francium/result-test
Author: francium
Author-email: francium@francium.cc
Maintainer: francium
License: MIT
Keywords: rust,result,enum
Platform: UNKNOWN
Classifier: Development Status :: 4 - Beta
Classifier: License :: OSI Approved :: MIT License
Classifier: Programming Language :: Python :: 3
Classifier: Programming Language :: Python :: 3.6
Classifier: Programming Language :: Python :: 3.7
Classifier: Programming Language :: Python :: 3.8
Classifier: Programming Language :: Python :: 3.9
Classifier: Programming Language :: Python :: 3.10
Classifier: Programming Language :: Python :: 3 :: Only
Requires-Python: >=3.6
License-File: LICENSE
